streamlit_sigmajs_component-1.0.2.dist-info/licenses/LICENSE
vsigma_component/__init__.py
vsigma_component/example.py
vsigma_component/local_data.py
vsigma_component/test_data.py
vsigma_component/public/dist/index.html
vsigma_component/public/dist/assets/index-XC8OQWlY.css
vsigma_component/public/dist/assets/index-fnabseS4.js
vsigma_component/vue_sigma/dist/index.html
vsigma_component/vue_sigma/dist/assets/index-B2EjDu7R.css
vsigma_component/vue_sigma/dist/assets/index-B63Q1Qe2.css
vsigma_component/vue_sigma/dist/assets/index-BideJ-YM.css
vsigma_component/vue_sigma/dist/assets/index-BkcpF2gi.js
vsigma_component/vue_sigma/dist/assets/index-Bsb8KK8K.js
vsigma_component/vue_sigma/dist/assets/index-BttoDqun.css
vsigma_component/vue_sigma/dist/assets/index-Bzx8oi8T.css
vsigma_component/vue_sigma/dist/assets/index-C_IiLHDR.js
vsigma_component/vue_sigma/dist/assets/index-CniZYDvI.js
vsigma_component/vue_sigma/dist/assets/index-DB-cVkz6.js
vsigma_component/vue_sigma/dist/assets/index-Ds7Sdny0.css
vsigma_component/vue_sigma/dist/assets/index-DtMh4d4s.js
vsigma_component/vue_sigma/dist/assets/index-EZLVaV0k.css
vsigma_component/vue_sigma/dist/assets/index-_eo80jPV.js
streamlit_sigmajs_component-1.0.2.dist-info/METADATA
streamlit_sigmajs_component-1.0.2.dist-info/WHEEL
streamlit_sigmajs_component-1.0.2.dist-info/top_level.txt
streamlit_sigmajs_component-1.0.2.dist-info/RECORD
