Metadata-Version: 2.4
Name: streamlit_sigmajs_component
Version: 1.0.2
Summary: A streamlit component to visualize network graph data using Sigma.js
Home-page: 
Author: camaris
Author-email: camaris <pypi@camaris.be>
License: MIT License
Project-URL: Homepage, https://github.com/camaris2/streamlit_sigmajs_component
Project-URL: Issues, https://github.com/camaris2/streamlit_sigmajs_component/issues
Classifier: Programming Language :: Python :: 3
Classifier: Operating System :: OS Independent
Requires-Python: >=3.7
License-File: LICENSE
Requires-Dist: streamlit>=0.63
Dynamic: author
Dynamic: license-file
Dynamic: requires-dist
Dynamic: requires-python
